LICENSE
ssh_assets/__init__.py
ssh_assets/authorized_keys/__init__.py
ssh_assets/authorized_keys/constants.py
ssh_assets/authorized_keys/loader.py
ssh_assets/authorized_keys/options.py
ssh_assets/authorized_keys/public_key.py
ssh_assets/base.py
ssh_assets/bin/__init__.py
ssh_assets/bin/base.py
ssh_assets/bin/ssh_assets/__init__.py
ssh_assets/bin/ssh_assets/groups/__init__.py
ssh_assets/bin/ssh_assets/groups/add.py
ssh_assets/bin/ssh_assets/groups/base.py
ssh_assets/bin/ssh_assets/groups/command.py
ssh_assets/bin/ssh_assets/groups/delete.py
ssh_assets/bin/ssh_assets/groups/edit.py
ssh_assets/bin/ssh_assets/groups/list.py
ssh_assets/bin/ssh_assets/keys/__init__.py
ssh_assets/bin/ssh_assets/keys/add.py
ssh_assets/bin/ssh_assets/keys/base.py
ssh_assets/bin/ssh_assets/keys/command.py
ssh_assets/bin/ssh_assets/keys/delete.py
ssh_assets/bin/ssh_assets/keys/edit.py
ssh_assets/bin/ssh_assets/keys/list.py
ssh_assets/bin/ssh_assets/keys/load.py
ssh_assets/bin/ssh_assets/keys/unload.py
ssh_assets/bin/ssh_assets/main.py
ssh_assets/configuration/__init__.py
ssh_assets/configuration/groups.py
ssh_assets/configuration/keys.py
ssh_assets/configuration/loader.py
ssh_assets/constants.py
ssh_assets/data/bash/ssh-assets.sh
ssh_assets/data/zsh/ssh_assets
ssh_assets/duration.py
ssh_assets/exceptions.py
ssh_assets/keys/__init__.py
ssh_assets/keys/agent.py
ssh_assets/keys/base.py
ssh_assets/keys/constants.py
ssh_assets/keys/file.py
ssh_assets/keys/filter_set.py
ssh_assets/session.py
ssh_assets/token/__init__.py
ssh_assets/token/base.py
ssh_assets/token/client.py
ssh_assets/token/server.py
ssh_assets-1.7.2.dist-info/LICENSE
ssh_assets-1.7.2.dist-info/METADATA
ssh_assets-1.7.2.dist-info/WHEEL
ssh_assets-1.7.2.dist-info/entry_points.txt
ssh_assets-1.7.2.dist-info/RECORD
